color_terminal_objc.cpython-39-darwin.so
color_terminal_objc-0.3.dist-info/METADATA
color_terminal_objc-0.3.dist-info/WHEEL
color_terminal_objc-0.3.dist-info/top_level.txt
color_terminal_objc-0.3.dist-info/RECORD
