Metadata-Version: 2.1
Name: color-terminal-objc
Version: 0.3
Summary: A Python package to print colored messages in terminal using Objective-C
Home-page: UNKNOWN
Author: Bobby
Author-email: info@bobby-shop.com
License: UNKNOWN
Platform: UNKNOWN
